{
  "action": {
    "description": "Hearing rescheduled to 03/16/2026 from 11:00 AM-12:10 PM in A-1   and Virtual Hearing updated to New End Time",
    "occurred_at": "2026-03-16",
    "jurisdiction_id": "~{\"classification\": \"legislature\"}",
    "session_id": "194th",
    "entity_type": "bill",
    "classifications": [],
    "related_entities": [],
    "sources": [
      {
        "url": "https://malegislature.gov/Bills/194/H5009",
        "note": ""
      }
    ]
  },
  "bill_id": "H5009"
}