{
  "action": {
    "description": "Hearing rescheduled to 11/18/2025 from 10:00 AM-11:00 AM in B-1                                             and Virtual Hearing updated to New End Time",
    "occurred_at": "2025-11-18",
    "jurisdiction_id": "~{\"classification\": \"legislature\"}",
    "session_id": "194th",
    "entity_type": "bill",
    "classifications": [],
    "related_entities": [],
    "sources": [
      {
        "url": "https://malegislature.gov/Bills/194/H3270",
        "note": ""
      }
    ]
  },
  "bill_id": "H3270"
}