{
  "action": {
    "description": "Referred to the committee on Revenue",
    "occurred_at": "2025-02-27",
    "jurisdiction_id": "~{\"classification\": \"lower\"}",
    "session_id": "194th",
    "entity_type": "bill",
    "classifications": [
      "referral-committee"
    ],
    "related_entities": [
      {
        "name": "committee on Revenue",
        "entity_type": "organization",
        "organization_id": null
      },
      {
        "name": "the committee on Revenue",
        "entity_type": "organization",
        "organization_id": null
      }
    ],
    "sources": [
      {
        "url": "https://malegislature.gov/Bills/194/H3227",
        "note": ""
      }
    ]
  },
  "bill_id": "H3227"
}